datasette_render_images.py
datasette_render_images-0.4.dist-info/METADATA
datasette_render_images-0.4.dist-info/WHEEL
datasette_render_images-0.4.dist-info/entry_points.txt
datasette_render_images-0.4.dist-info/top_level.txt
datasette_render_images-0.4.dist-info/RECORD
