Metadata-Version: 2.1
Name: datasette-render-images
Version: 0.4
Summary: Datasette plugin that renders binary blob images using data-uris
Home-page: https://github.com/simonw/datasette-render-images
Author: Simon Willison
License: Apache License, Version 2.0
Requires-Dist: datasette
Provides-Extra: test
Requires-Dist: pytest ; extra == 'test'
